md2pdf/__init__.py
md2pdf/cli.py
md2pdf/converter.py
md2pdf/gui.py
md2pdf_advanced-0.1.0.dist-info/METADATA
md2pdf_advanced-0.1.0.dist-info/WHEEL
md2pdf_advanced-0.1.0.dist-info/entry_points.txt
md2pdf_advanced-0.1.0.dist-info/top_level.txt
md2pdf_advanced-0.1.0.dist-info/RECORD
