Metadata-Version: 2.4
Name: md2pdf-advanced
Version: 0.1.0
Summary: Convert Markdown to PDF via CLI and GUI (with optional AI summary)
Author-email: Yuto TAKAGI <yutotakagi.for.business@email.com>
License: MIT
Requires-Python: >=3.11
Requires-Dist: markdown
Requires-Dist: weasyprint>=60.0
Requires-Dist: jinja2
Requires-Dist: typer[all]
Requires-Dist: streamlit
